[{"date":"1996-03-31","country":"EU15","values":"1.47532612672"},{"date":"1996-06-30","country":"EU15","values":"1.7225873792"},{"date":"1996-09-30","country":"EU15","values":"2.13992394899"},{"date":"1996-12-31","country":"EU15","values":"1.80411661738"},{"date":"1997-03-31","country":"EU15","values":"1.32315963117"},{"date":"1997-06-30","country":"EU15","values":"3.3710573021"},{"date":"1997-09-30","country":"EU15","values":"2.85068311139"},{"date":"1997-12-31","country":"EU15","values":"3.64260366542"},{"date":"1998-03-31","country":"EU15","values":"3.88228576787"},{"date":"1998-06-30","country":"EU15","values":"2.4691941749"},{"date":"1998-09-30","country":"EU15","values":"2.98005136569"},{"date":"1998-12-31","country":"EU15","values":"2.42104289677"},{"date":"1999-03-31","country":"EU15","values":"2.32357290174"},{"date":"1999-06-30","country":"EU15","values":"2.85748585976"},{"date":"1999-09-30","country":"EU15","values":"2.87694650811"},{"date":"1999-12-31","country":"EU15","values":"3.633002094"},{"date":"2000-03-31","country":"EU15","values":"5.01176843477"},{"date":"2000-06-30","country":"EU15","values":"4.34029813194"},{"date":"2000-09-30","country":"EU15","values":"3.47817167082"},{"date":"2000-12-31","country":"EU15","values":"2.8525540245"},{"date":"2001-03-31","country":"EU15","values":"2.47742220308"},{"date":"2001-06-30","country":"EU15","values":"1.65856918621"},{"date":"2001-09-30","country":"EU15","values":"1.64666373839"},{"date":"2001-12-31","country":"EU15","values":"2.05615008702"},{"date":"2002-03-31","country":"EU15","values":"0.83101550516"},{"date":"2002-06-30","country":"EU15","values":"1.3597147704"},{"date":"2002-09-30","country":"EU15","values":"1.68675076312"},{"date":"2002-12-31","country":"EU15","values":"0.823211301484"},{"date":"2003-03-31","country":"EU15","values":"1.26263491042"},{"date":"2003-06-30","country":"EU15","values":"1.00544772414"},{"date":"2003-09-30","country":"EU15","values":"1.17091329966"},{"date":"2003-12-31","country":"EU15","values":"1.82720875932"},{"date":"2004-03-31","country":"EU15","values":"2.41714690242"},{"date":"2004-06-30","country":"EU15","values":"2.85683979691"},{"date":"2004-09-30","country":"EU15","values":"2.25246657569"},{"date":"2004-12-31","country":"EU15","values":"2.12503566125"},{"date":"2005-03-31","country":"EU15","values":"1.48052093949"},{"date":"2005-06-30","country":"EU15","values":"1.95567487861"},{"date":"2005-09-30","country":"EU15","values":"2.35483855335"},{"date":"2005-12-31","country":"EU15","values":"2.21268403273"},{"date":"2006-03-31","country":"EU15","values":"3.39267363792"},{"date":"2006-06-30","country":"EU15","values":"3.02353561338"},{"date":"2006-09-30","country":"EU15","values":"2.90512568566"},{"date":"2006-12-31","country":"EU15","values":"3.32456964316"},{"date":"2007-03-31","country":"EU15","values":"3.24804204942"},{"date":"2007-06-30","country":"EU15","values":"3.0093263528"},{"date":"2007-09-30","country":"EU15","values":"3.17672344235"},{"date":"2007-12-31","country":"EU15","values":"2.5838998183"},{"date":"2008-03-31","country":"EU15","values":"1.74942677476"},{"date":"2008-06-30","country":"EU15","values":"1.32301197612"},{"date":"2008-09-30","country":"EU15","values":"-0.0229713757298"},{"date":"2008-12-31","country":"EU15","values":"-2.60166305549"},{"date":"2009-03-31","country":"EU15","values":"-5.73509610569"},{"date":"2009-06-30","country":"EU15","values":"-5.95882190636"},{"date":"2009-09-30","country":"EU15","values":"-4.42884430224"},{"date":"2009-12-31","country":"EU15","values":"-2.13836241262"},{"date":"2010-03-31","country":"EU15","values":"1.05816473263"},{"date":"2010-06-30","country":"EU15","values":"2.466081124"},{"date":"2010-09-30","country":"EU15","values":"2.3697902072"},{"date":"2010-12-31","country":"EU15","values":"2.13190410631"},{"date":"2011-03-31","country":"EU15","values":"2.63918202987"},{"date":"2011-06-30","country":"EU15","values":"1.77963717743"},{"date":"2011-09-30","country":"EU15","values":"1.33902297759"},{"date":"2011-12-31","country":"EU15","values":"0.422916556197"},{"date":"2012-03-31","country":"EU15","values":"0.504232112953"},{"date":"2012-06-30","country":"EU15","values":"-0.800840270696"},{"date":"2012-09-30","country":"EU15","values":"-0.73008994405"},{"date":"2012-12-31","country":"EU15","values":"-0.987189783753"},{"date":"2013-03-31","country":"EU15","values":"-1.52475323806"},{"date":"2013-06-30","country":"EU15","values":"-0.223940076734"},{"date":"2013-09-30","country":"EU15","values":"0.214644260924"}]