[{"date":"1995-03-31","country":"SK","values":"2649.6"},{"date":"1995-06-30","country":"SK","values":"2928.7"},{"date":"1995-09-30","country":"SK","values":"2758.3"},{"date":"1995-12-31","country":"SK","values":"2822.7"},{"date":"1996-03-31","country":"SK","values":"2979.9"},{"date":"1996-06-30","country":"SK","values":"3066.1"},{"date":"1996-09-30","country":"SK","values":"3137.5"},{"date":"1996-12-31","country":"SK","values":"3219.2"},{"date":"1997-03-31","country":"SK","values":"3345.4"},{"date":"1997-06-30","country":"SK","values":"3461.7"},{"date":"1997-09-30","country":"SK","values":"3603.3"},{"date":"1997-12-31","country":"SK","values":"3607.4"},{"date":"1998-03-31","country":"SK","values":"3688.5"},{"date":"1998-06-30","country":"SK","values":"3775.6"},{"date":"1998-09-30","country":"SK","values":"3767.4"},{"date":"1998-12-31","country":"SK","values":"3588.5"},{"date":"1999-03-31","country":"SK","values":"3549.6"},{"date":"1999-06-30","country":"SK","values":"3456.1"},{"date":"1999-09-30","country":"SK","values":"3550.8"},{"date":"1999-12-31","country":"SK","values":"3679.2"},{"date":"2000-03-31","country":"SK","values":"3947.7"},{"date":"2000-06-30","country":"SK","values":"4058.8"},{"date":"2000-09-30","country":"SK","values":"4131.1"},{"date":"2000-12-31","country":"SK","values":"4186.6"},{"date":"2001-03-31","country":"SK","values":"4199.1"},{"date":"2001-06-30","country":"SK","values":"4382.9"},{"date":"2001-09-30","country":"SK","values":"4424.2"},{"date":"2001-12-31","country":"SK","values":"4523.8"},{"date":"2002-03-31","country":"SK","values":"4707.8"},{"date":"2002-06-30","country":"SK","values":"4707.9"},{"date":"2002-09-30","country":"SK","values":"4785.8"},{"date":"2002-12-31","country":"SK","values":"5126.0"},{"date":"2003-03-31","country":"SK","values":"5218.8"},{"date":"2003-06-30","country":"SK","values":"5470.3"},{"date":"2003-09-30","country":"SK","values":"5496.7"},{"date":"2003-12-31","country":"SK","values":"5747.2"},{"date":"2004-03-31","country":"SK","values":"6065.2"},{"date":"2004-06-30","country":"SK","values":"6159.2"},{"date":"2004-09-30","country":"SK","values":"6392.7"},{"date":"2004-12-31","country":"SK","values":"6652.0"},{"date":"2005-03-31","country":"SK","values":"6950.7"},{"date":"2005-06-30","country":"SK","values":"7007.9"},{"date":"2005-09-30","country":"SK","values":"7205.4"},{"date":"2005-12-31","country":"SK","values":"7418.0"},{"date":"2006-03-31","country":"SK","values":"7777.8"},{"date":"2006-06-30","country":"SK","values":"8073.7"},{"date":"2006-09-30","country":"SK","values":"8233.8"},{"date":"2006-12-31","country":"SK","values":"8968.5"},{"date":"2007-03-31","country":"SK","values":"9569.2"},{"date":"2007-06-30","country":"SK","values":"9976.9"},{"date":"2007-09-30","country":"SK","values":"10354.2"},{"date":"2007-12-31","country":"SK","values":"10742.2"},{"date":"2008-03-31","country":"SK","values":"11180.6"},{"date":"2008-06-30","country":"SK","values":"11895.6"},{"date":"2008-09-30","country":"SK","values":"12363.3"},{"date":"2008-12-31","country":"SK","values":"12255.8"},{"date":"2009-03-31","country":"SK","values":"11437.3"},{"date":"2009-06-30","country":"SK","values":"11489.2"},{"date":"2009-09-30","country":"SK","values":"11630.9"},{"date":"2009-12-31","country":"SK","values":"11804.2"},{"date":"2010-03-31","country":"SK","values":"11906.4"},{"date":"2010-06-30","country":"SK","values":"12050.2"},{"date":"2010-09-30","country":"SK","values":"12263.6"},{"date":"2010-12-31","country":"SK","values":"12322.6"},{"date":"2011-03-31","country":"SK","values":"12546.3"},{"date":"2011-06-30","country":"SK","values":"12735.5"},{"date":"2011-09-30","country":"SK","values":"12816.2"},{"date":"2011-12-31","country":"SK","values":"13011.2"},{"date":"2012-03-31","country":"SK","values":"13055.2"},{"date":"2012-06-30","country":"SK","values":"13121.7"},{"date":"2012-09-30","country":"SK","values":"13212.4"},{"date":"2012-12-31","country":"SK","values":"13213.4"},{"date":"2013-03-31","country":"SK","values":"13248.3"},{"date":"2013-06-30","country":"SK","values":"13314.7"},{"date":"2013-09-30","country":"SK","values":"13343.3"},{"date":"2013-12-31","country":"SK","values":"13398.0"}]